{
  "targets": [
    {
      "name": "other",
      "frames": [
        {
          "time": 0.0,
          "duration": 1.0,
          "metrics": {
            "SDR": 2.54779,
            "SIR": 11.31272,
            "SAR": 3.42000,
            "ISR": 29.58112
          }
        },
        {
          "time": 1.0,
          "duration": 1.0,
          "metrics": {
            "SDR": -10.95654,
            "SIR": -10.66731,
            "SAR": 11.27233,
            "ISR": 17.74478
          }
        },
        {
          "time": 2.0,
          "duration": 1.0,
          "metrics": {
            "SDR": -11.82150,
            "SIR": -11.70256,
            "SAR": 25.19496,
            "ISR": 17.29175
          }
        },
        {
          "time": 3.0,
          "duration": 1.0,
          "metrics": {
            "SDR": -11.93873,
            "SIR": -11.93922,
            "SAR": 37.40813,
            "ISR": 18.50209
          }
        },
        {
          "time": 4.0,
          "duration": 1.0,
          "metrics": {
            "SDR": -11.26523,
            "SIR": -11.16561,
            "SAR": 36.59463,
            "ISR": 16.95361
          }
        },
        {
          "time": 5.0,
          "duration": 1.0,
          "metrics": {
            "SDR": -9.87149,
            "SIR": -9.44448,
            "SAR": 9.95961,
            "ISR": 22.37771
          }
        },
        {
          "time": 6.0,
          "duration": 1.0,
          "metrics": {
            "SDR": -7.22954,
            "SIR": -5.55985,
            "SAR": 4.60725,
            "ISR": 20.01187
          }
        },
        {
          "time": 7.0,
          "duration": 1.0,
          "metrics": {
            "SDR": -1.95505,
            "SIR": -1.61013,
            "SAR": 10.80447,
            "ISR": 20.01394
          }
        },
        {
          "time": 8.0,
          "duration": 1.0,
          "metrics": {
            "SDR": -7.13329,
            "SIR": -7.15811,
            "SAR": 33.03766,
            "ISR": 20.90545
          }
        },
        {
          "time": 9.0,
          "duration": 1.0,
          "metrics": {
            "SDR": -4.58341,
            "SIR": -4.60969,
            "SAR": 32.01066,
            "ISR": 23.95342
          }
        },
        {
          "time": 10.0,
          "duration": 1.0,
          "metrics": {
            "SDR": -7.56293,
            "SIR": -6.92489,
            "SAR": 8.89936,
            "ISR": 24.22161
          }
        },
        {
          "time": 11.0,
          "duration": 1.0,
          "metrics": {
            "SDR": -5.13518,
            "SIR": -4.05198,
            "SAR": 6.22052,
            "ISR": 22.04221
          }
        },
        {
          "time": 12.0,
          "duration": 1.0,
          "metrics": {
            "SDR": -5.32414,
            "SIR": -5.31608,
            "SAR": 24.11965,
            "ISR": 22.76280
          }
        },
        {
          "time": 13.0,
          "duration": 1.0,
          "metrics": {
            "SDR": -9.49587,
            "SIR": -8.49668,
            "SAR": 6.33135,
            "ISR": 24.80339
          }
        },
        {
          "time": 14.0,
          "duration": 1.0,
          "metrics": {
            "SDR": -6.48131,
            "SIR": -6.33245,
            "SAR": 14.12554,
            "ISR": 25.02400
          }
        },
        {
          "time": 15.0,
          "duration": 1.0,
          "metrics": {
            "SDR": -9.25147,
            "SIR": -8.49937,
            "SAR": 8.13432,
            "ISR": 21.34165
          }
        },
        {
          "time": 16.0,
          "duration": 1.0,
          "metrics": {
            "SDR": -9.77599,
            "SIR": -8.84281,
            "SAR": 6.75263,
            "ISR": 19.64123
          }
        },
        {
          "time": 17.0,
          "duration": 1.0,
          "metrics": {
            "SDR": -10.12925,
            "SIR": -9.72990,
            "SAR": 10.71033,
            "ISR": 22.12525
          }
        },
        {
          "time": 18.0,
          "duration": 1.0,
          "metrics": {
            "SDR": -4.55744,
            "SIR": -2.96277,
            "SAR": 5.39594,
            "ISR": 24.48092
          }
        },
        {
          "time": 19.0,
          "duration": 1.0,
          "metrics": {
            "SDR": 2.59344,
            "SIR": 11.81658,
            "SAR": 3.44736,
            "ISR": 31.00895
          }
        },
        {
          "time": 20.0,
          "duration": 1.0,
          "metrics": {
            "SDR": -10.80141,
            "SIR": -10.36715,
            "SAR": 9.71343,
            "ISR": 17.13254
          }
        },
        {
          "time": 21.0,
          "duration": 1.0,
          "metrics": {
            "SDR": -11.42640,
            "SIR": -11.30228,
            "SAR": 23.97510,
            "ISR": 17.62289
          }
        },
        {
          "time": 22.0,
          "duration": 1.0,
          "metrics": {
            "SDR": -10.73754,
            "SIR": -10.70637,
            "SAR": 36.36830,
            "ISR": 20.91213
          }
        },
        {
          "time": 23.0,
          "duration": 1.0,
          "metrics": {
            "SDR": -9.81343,
            "SIR": -9.84178,
            "SAR": 36.53190,
            "ISR": 17.62347
          }
        },
        {
          "time": 24.0,
          "duration": 1.0,
          "metrics": {
            "SDR": -9.49727,
            "SIR": -9.16725,
            "SAR": 11.21250,
            "ISR": 23.52949
          }
        },
        {
          "time": 25.0,
          "duration": 1.0,
          "metrics": {
            "SDR": -9.10856,
            "SIR": -7.97743,
            "SAR": 5.76763,
            "ISR": 20.77000
          }
        },
        {
          "time": 26.0,
          "duration": 1.0,
          "metrics": {
            "SDR": -2.99984,
            "SIR": -2.29064,
            "SAR": 9.22884,
            "ISR": 21.95002
          }
        },
        {
          "time": 27.0,
          "duration": 1.0,
          "metrics": {
            "SDR": -9.03416,
            "SIR": -9.02222,
            "SAR": 32.60015,
            "ISR": 23.60105
          }
        },
        {
          "time": 28.0,
          "duration": 1.0,
          "metrics": {
            "SDR": -6.20093,
            "SIR": -6.24721,
            "SAR": 32.76419,
            "ISR": 19.74193
          }
        },
        {
          "time": 29.0,
          "duration": 1.0,
          "metrics": {
            "SDR": -7.37983,
            "SIR": -6.82474,
            "SAR": 9.27299,
            "ISR": 20.60515
          }
        },
        {
          "time": 30.0,
          "duration": 1.0,
          "metrics": {
            "SDR": -5.93361,
            "SIR": -4.21380,
            "SAR": 4.47171,
            "ISR": 25.53254
          }
        },
        {
          "time": 31.0,
          "duration": 1.0,
          "metrics": {
            "SDR": -6.53915,
            "SIR": -6.52299,
            "SAR": 21.88868,
            "ISR": 26.00112
          }
        },
        {
          "time": 32.0,
          "duration": 1.0,
          "metrics": {
            "SDR": -9.37758,
            "SIR": -8.73045,
            "SAR": 8.06252,
            "ISR": 23.63584
          }
        },
        {
          "time": 33.0,
          "duration": 1.0,
          "metrics": {
            "SDR": -6.40902,
            "SIR": -6.38629,
            "SAR": 21.80498,
            "ISR": 23.60689
          }
        },
        {
          "time": 34.0,
          "duration": 1.0,
          "metrics": {
            "SDR": -10.95217,
            "SIR": -10.32351,
            "SAR": 8.65831,
            "ISR": 21.82047
          }
        },
        {
          "time": 35.0,
          "duration": 1.0,
          "metrics": {
            "SDR": -9.26628,
            "SIR": -8.56444,
            "SAR": 8.06380,
            "ISR": 20.77660
          }
        },
        {
          "time": 36.0,
          "duration": 1.0,
          "metrics": {
            "SDR": -10.38176,
            "SIR": -9.97508,
            "SAR": 9.95935,
            "ISR": 21.90544
          }
        },
        {
          "time": 37.0,
          "duration": 1.0,
          "metrics": {
            "SDR": -8.79405,
            "SIR": -7.61248,
            "SAR": 6.24667,
            "ISR": 21.26001
          }
        },
        {
          "time": 38.0,
          "duration": 1.0,
          "metrics": {
            "SDR": -0.94390,
            "SIR": 9.81137,
            "SAR": -0.19608,
            "ISR": 31.15406
          }
        },
        {
          "time": 39.0,
          "duration": 1.0,
          "metrics": {
            "SDR": -9.60591,
            "SIR": -9.39247,
            "SAR": 12.16670,
            "ISR": 20.65433
          }
        },
        {
          "time": 40.0,
          "duration": 1.0,
          "metrics": {
            "SDR": -10.94860,
            "SIR": -10.84495,
            "SAR": 22.14199,
            "ISR": 18.27180
          }
        },
        {
          "time": 41.0,
          "duration": 1.0,
          "metrics": {
            "SDR": -10.97942,
            "SIR": -10.99001,
            "SAR": 21.95189,
            "ISR": 20.71752
          }
        },
        {
          "time": 42.0,
          "duration": 1.0,
          "metrics": {
            "SDR": -10.29325,
            "SIR": -10.08267,
            "SAR": 28.13127,
            "ISR": 16.66348
          }
        },
        {
          "time": 43.0,
          "duration": 1.0,
          "metrics": {
            "SDR": -9.60947,
            "SIR": -8.99539,
            "SAR": 8.46517,
            "ISR": 24.36174
          }
        },
        {
          "time": 44.0,
          "duration": 1.0,
          "metrics": {
            "SDR": -9.39385,
            "SIR": -8.33373,
            "SAR": 5.86842,
            "ISR": 20.71134
          }
        },
        {
          "time": 45.0,
          "duration": 1.0,
          "metrics": {
            "SDR": -8.90112,
            "SIR": -8.29374,
            "SAR": 8.25480,
            "ISR": 21.54114
          }
        },
        {
          "time": 46.0,
          "duration": 1.0,
          "metrics": {
            "SDR": -10.71281,
            "SIR": -10.38992,
            "SAR": 11.50700,
            "ISR": 22.94457
          }
        },
        {
          "time": 47.0,
          "duration": 1.0,
          "metrics": {
            "SDR": -8.65044,
            "SIR": -8.66973,
            "SAR": 19.60988,
            "ISR": 20.74534
          }
        },
        {
          "time": 48.0,
          "duration": 1.0,
          "metrics": {
            "SDR": -9.20367,
            "SIR": -9.12402,
            "SAR": 16.09217,
            "ISR": 23.72490
          }
        },
        {
          "time": 49.0,
          "duration": 1.0,
          "metrics": {
            "SDR": -7.81587,
            "SIR": -6.11162,
            "SAR": 4.09208,
            "ISR": 23.43433
          }
        },
        {
          "time": 50.0,
          "duration": 1.0,
          "metrics": {
            "SDR": -5.74929,
            "SIR": -5.66396,
            "SAR": 17.48260,
            "ISR": 22.51159
          }
        },
        {
          "time": 51.0,
          "duration": 1.0,
          "metrics": {
            "SDR": -8.47342,
            "SIR": -8.01878,
            "SAR": 9.85393,
            "ISR": 20.61379
          }
        },
        {
          "time": 52.0,
          "duration": 1.0,
          "metrics": {
            "SDR": -6.61085,
            "SIR": -6.34408,
            "SAR": 12.33822,
            "ISR": 22.97965
          }
        },
        {
          "time": 53.0,
          "duration": 1.0,
          "metrics": {
            "SDR": -8.84203,
            "SIR": -8.49785,
            "SAR": 11.82657,
            "ISR": 22.59179
          }
        },
        {
          "time": 54.0,
          "duration": 1.0,
          "metrics": {
            "SDR": -9.33879,
            "SIR": -8.75672,
            "SAR": 8.88906,
            "ISR": 20.79523
          }
        },
        {
          "time": 55.0,
          "duration": 1.0,
          "metrics": {
            "SDR": -8.78261,
            "SIR": -8.18533,
            "SAR": 9.02033,
            "ISR": 23.75859
          }
        },
        {
          "time": 56.0,
          "duration": 1.0,
          "metrics": {
            "SDR": -8.60598,
            "SIR": -8.29047,
            "SAR": 12.39547,
            "ISR": 20.20636
          }
        },
        {
          "time": 57.0,
          "duration": 1.0,
          "metrics": {
            "SDR": 5.15280,
            "SIR": 6.74306,
            "SAR": 10.66380,
            "ISR": 19.47800
          }
        },
        {
          "time": 58.0,
          "duration": 1.0,
          "metrics": {
            "SDR": -6.01348,
            "SIR": -4.97489,
            "SAR": 6.66398,
            "ISR": 24.41524
          }
        },
        {
          "time": 59.0,
          "duration": 1.0,
          "metrics": {
            "SDR": -6.00487,
            "SIR": -4.85249,
            "SAR": 6.22613,
            "ISR": 23.52192
          }
        },
        {
          "time": 60.0,
          "duration": 1.0,
          "metrics": {
            "SDR": -5.44459,
            "SIR": -5.34581,
            "SAR": 17.38324,
            "ISR": 26.84805
          }
        },
        {
          "time": 61.0,
          "duration": 1.0,
          "metrics": {
            "SDR": -5.90569,
            "SIR": -4.49843,
            "SAR": 5.46351,
            "ISR": 27.90226
          }
        },
        {
          "time": 62.0,
          "duration": 1.0,
          "metrics": {
            "SDR": -3.82192,
            "SIR": -3.46292,
            "SAR": 11.47796,
            "ISR": 27.11341
          }
        },
        {
          "time": 63.0,
          "duration": 1.0,
          "metrics": {
            "SDR": -4.85244,
            "SIR": -4.10421,
            "SAR": 8.63238,
            "ISR": 28.19048
          }
        },
        {
          "time": 64.0,
          "duration": 1.0,
          "metrics": {
            "SDR": -4.14870,
            "SIR": -3.25947,
            "SAR": 7.98600,
            "ISR": 23.51678
          }
        },
        {
          "time": 65.0,
          "duration": 1.0,
          "metrics": {
            "SDR": -2.82926,
            "SIR": -2.44791,
            "SAR": 12.37399,
            "ISR": 23.78891
          }
        },
        {
          "time": 66.0,
          "duration": 1.0,
          "metrics": {
            "SDR": -4.21198,
            "SIR": -2.96089,
            "SAR": 6.48746,
            "ISR": 29.48306
          }
        },
        {
          "time": 67.0,
          "duration": 1.0,
          "metrics": {
            "SDR": -3.85088,
            "SIR": -3.49376,
            "SAR": 11.91363,
            "ISR": 30.15880
          }
        },
        {
          "time": 68.0,
          "duration": 1.0,
          "metrics": {
            "SDR": -5.45375,
            "SIR": -4.71440,
            "SAR": 8.34308,
            "ISR": 26.97860
          }
        },
        {
          "time": 69.0,
          "duration": 1.0,
          "metrics": {
            "SDR": -4.63752,
            "SIR": -3.92384,
            "SAR": 8.94838,
            "ISR": 25.77596
          }
        },
        {
          "time": 70.0,
          "duration": 1.0,
          "metrics": {
            "SDR": -3.96445,
            "SIR": -3.44934,
            "SAR": 10.49079,
            "ISR": 26.86775
          }
        },
        {
          "time": 71.0,
          "duration": 1.0,
          "metrics": {
            "SDR": -4.48362,
            "SIR": -3.50084,
            "SAR": 7.48716,
            "ISR": 26.42843
          }
        },
        {
          "time": 72.0,
          "duration": 1.0,
          "metrics": {
            "SDR": -3.99596,
            "SIR": -3.29844,
            "SAR": 9.06259,
            "ISR": 25.80659
          }
        },
        {
          "time": 73.0,
          "duration": 1.0,
          "metrics": {
            "SDR": -6.07925,
            "SIR": -4.80123,
            "SAR": 5.83419,
            "ISR": 27.76511
          }
        },
        {
          "time": 74.0,
          "duration": 1.0,
          "metrics": {
            "SDR": -4.96951,
            "SIR": -4.16753,
            "SAR": 8.08035,
            "ISR": 26.59694
          }
        },
        {
          "time": 75.0,
          "duration": 1.0,
          "metrics": {
            "SDR": -3.72948,
            "SIR": -3.33595,
            "SAR": 11.61953,
            "ISR": 26.36978
          }
        },
        {
          "time": 76.0,
          "duration": 1.0,
          "metrics": {
            "SDR": -2.96591,
            "SIR": -2.66953,
            "SAR": 13.11129,
            "ISR": 29.12334
          }
        },
        {
          "time": 77.0,
          "duration": 1.0,
          "metrics": {
            "SDR": -4.31532,
            "SIR": -3.68109,
            "SAR": 9.39768,
            "ISR": 21.84713
          }
        },
        {
          "time": 78.0,
          "duration": 1.0,
          "metrics": {
            "SDR": -4.36904,
            "SIR": -3.00454,
            "SAR": 6.08136,
            "ISR": 21.76983
          }
        },
        {
          "time": 79.0,
          "duration": 1.0,
          "metrics": {
            "SDR": -1.90999,
            "SIR": -1.17218,
            "SAR": 9.35910,
            "ISR": 26.01687
          }
        },
        {
          "time": 80.0,
          "duration": 1.0,
          "metrics": {
            "SDR": -4.04880,
            "SIR": -2.88781,
            "SAR": 6.68749,
            "ISR": 28.09503
          }
        },
        {
          "time": 81.0,
          "duration": 1.0,
          "metrics": {
            "SDR": -1.93142,
            "SIR": -1.08674,
            "SAR": 9.06048,
            "ISR": 25.02012
          }
        },
        {
          "time": 82.0,
          "duration": 1.0,
          "metrics": {
            "SDR": -5.97528,
            "SIR": -5.40446,
            "SAR": 9.53898,
            "ISR": 23.57954
          }
        },
        {
          "time": 83.0,
          "duration": 1.0,
          "metrics": {
            "SDR": -4.58712,
            "SIR": -3.80114,
            "SAR": 8.42103,
            "ISR": 27.72644
          }
        },
        {
          "time": 84.0,
          "duration": 1.0,
          "metrics": {
            "SDR": -3.17768,
            "SIR": -2.58467,
            "SAR": 10.17902,
            "ISR": 28.04782
          }
        },
        {
          "time": 85.0,
          "duration": 1.0,
          "metrics": {
            "SDR": -3.54200,
            "SIR": -2.17059,
            "SAR": 6.29158,
            "ISR": 24.84019
          }
        },
        {
          "time": 86.0,
          "duration": 1.0,
          "metrics": {
            "SDR": -4.12425,
            "SIR": -3.42584,
            "SAR": 9.16067,
            "ISR": 24.28587
          }
        },
        {
          "time": 87.0,
          "duration": 1.0,
          "metrics": {
            "SDR": -5.86561,
            "SIR": -4.87739,
            "SAR": 6.99561,
            "ISR": 29.18790
          }
        },
        {
          "time": 88.0,
          "duration": 1.0,
          "metrics": {
            "SDR": -5.39936,
            "SIR": -4.79049,
            "SAR": 9.21059,
            "ISR": 27.58426
          }
        },
        {
          "time": 89.0,
          "duration": 1.0,
          "metrics": {
            "SDR": -4.29596,
            "SIR": -3.36323,
            "SAR": 7.74167,
            "ISR": 29.22453
          }
        },
        {
          "time": 90.0,
          "duration": 1.0,
          "metrics": {
            "SDR": -4.54571,
            "SIR": -3.73638,
            "SAR": 8.31959,
            "ISR": 26.60689
          }
        },
        {
          "time": 91.0,
          "duration": 1.0,
          "metrics": {
            "SDR": -5.12439,
            "SIR": -4.55912,
            "SAR": 9.82294,
            "ISR": 25.42402
          }
        },
        {
          "time": 92.0,
          "duration": 1.0,
          "metrics": {
            "SDR": -4.86324,
            "SIR": -3.86875,
            "SAR": 7.26938,
            "ISR": 28.18999
          }
        },
        {
          "time": 93.0,
          "duration": 1.0,
          "metrics": {
            "SDR": -2.65513,
            "SIR": -0.99021,
            "SAR": 5.75880,
            "ISR": 28.73186
          }
        },
        {
          "time": 94.0,
          "duration": 1.0,
          "metrics": {
            "SDR": -4.81996,
            "SIR": -3.88229,
            "SAR": 7.56273,
            "ISR": 28.92212
          }
        },
        {
          "time": 95.0,
          "duration": 1.0,
          "metrics": {
            "SDR": -4.13892,
            "SIR": -3.57299,
            "SAR": 9.97222,
            "ISR": 27.15039
          }
        },
        {
          "time": 96.0,
          "duration": 1.0,
          "metrics": {
            "SDR": -0.59505,
            "SIR": -0.24909,
            "SAR": 13.80913,
            "ISR": 27.27173
          }
        },
        {
          "time": 97.0,
          "duration": 1.0,
          "metrics": {
            "SDR": 0.27149,
            "SIR": 0.27242,
            "SAR": 21.71744,
            "ISR": 28.40187
          }
        },
        {
          "time": 98.0,
          "duration": 1.0,
          "metrics": {
            "SDR": -0.20088,
            "SIR": -0.20315,
            "SAR": 27.21515,
            "ISR": 29.65421
          }
        },
        {
          "time": 99.0,
          "duration": 1.0,
          "metrics": {
            "SDR": -0.60164,
            "SIR": -0.69069,
            "SAR": 30.74701,
            "ISR": 27.31981
          }
        },
        {
          "time": 100.0,
          "duration": 1.0,
          "metrics": {
            "SDR": 0.13361,
            "SIR": 0.08929,
            "SAR": 30.57476,
            "ISR": 28.04476
          }
        },
        {
          "time": 101.0,
          "duration": 1.0,
          "metrics": {
            "SDR": 0.68857,
            "SIR": 0.67370,
            "SAR": 30.39669,
            "ISR": 28.77818
          }
        },
        {
          "time": 102.0,
          "duration": 1.0,
          "metrics": {
            "SDR": 0.86924,
            "SIR": 0.87497,
            "SAR": 30.56955,
            "ISR": 30.13537
          }
        },
        {
          "time": 103.0,
          "duration": 1.0,
          "metrics": {
            "SDR": 1.64866,
            "SIR": 1.63639,
            "SAR": 31.39814,
            "ISR": 30.82450
          }
        },
        {
          "time": 104.0,
          "duration": 1.0,
          "metrics": {
            "SDR": 2.03258,
            "SIR": 2.04696,
            "SAR": 30.43493,
            "ISR": 29.58058
          }
        },
        {
          "time": 105.0,
          "duration": 1.0,
          "metrics": {
            "SDR": 2.42586,
            "SIR": 2.41600,
            "SAR": 29.68935,
            "ISR": 30.64806
          }
        },
        {
          "time": 106.0,
          "duration": 1.0,
          "metrics": {
            "SDR": 2.32280,
            "SIR": 2.38288,
            "SAR": 30.53676,
            "ISR": 28.55537
          }
        },
        {
          "time": 107.0,
          "duration": 1.0,
          "metrics": {
            "SDR": 1.90661,
            "SIR": 1.86265,
            "SAR": 30.98391,
            "ISR": 27.84208
          }
        },
        {
          "time": 108.0,
          "duration": 1.0,
          "metrics": {
            "SDR": 3.26052,
            "SIR": 3.22074,
            "SAR": 29.99017,
            "ISR": 29.28539
          }
        },
        {
          "time": 109.0,
          "duration": 1.0,
          "metrics": {
            "SDR": 1.75962,
            "SIR": 1.72198,
            "SAR": 29.82755,
            "ISR": 29.50198
          }
        },
        {
          "time": 110.0,
          "duration": 1.0,
          "metrics": {
            "SDR": -1.63015,
            "SIR": -1.64068,
            "SAR": 31.55455,
            "ISR": 29.78475
          }
        },
        {
          "time": 111.0,
          "duration": 1.0,
          "metrics": {
            "SDR": -1.13618,
            "SIR": -1.21118,
            "SAR": 31.87461,
            "ISR": 27.99235
          }
        },
        {
          "time": 112.0,
          "duration": 1.0,
          "metrics": {
            "SDR": -2.35820,
            "SIR": -2.37915,
            "SAR": 31.91932,
            "ISR": 27.09767
          }
        },
        {
          "time": 113.0,
          "duration": 1.0,
          "metrics": {
            "SDR": -2.59487,
            "SIR": -2.57498,
            "SAR": 31.46850,
            "ISR": 26.29355
          }
        },
        {
          "time": 114.0,
          "duration": 1.0,
          "metrics": {
            "SDR": -0.85118,
            "SIR": -0.87528,
            "SAR": 30.56238,
            "ISR": 26.52368
          }
        },
        {
          "time": 115.0,
          "duration": 1.0,
          "metrics": {
            "SDR": -1.09396,
            "SIR": -1.08009,
            "SAR": 31.83871,
            "ISR": 27.00360
          }
        },
        {
          "time": 116.0,
          "duration": 1.0,
          "metrics": {
            "SDR": -1.40082,
            "SIR": -1.42342,
            "SAR": 32.11851,
            "ISR": 28.47988
          }
        },
        {
          "time": 117.0,
          "duration": 1.0,
          "metrics": {
            "SDR": -1.37229,
            "SIR": -1.40726,
            "SAR": 32.24336,
            "ISR": 26.25018
          }
        },
        {
          "time": 118.0,
          "duration": 1.0,
          "metrics": {
            "SDR": -0.76492,
            "SIR": -0.76060,
            "SAR": 30.83467,
            "ISR": 26.39048
          }
        },
        {
          "time": 119.0,
          "duration": 1.0,
          "metrics": {
            "SDR": 0.25797,
            "SIR": 0.26335,
            "SAR": 30.23560,
            "ISR": 29.48172
          }
        },
        {
          "time": 120.0,
          "duration": 1.0,
          "metrics": {
            "SDR": 1.03132,
            "SIR": 0.97977,
            "SAR": 30.63077,
            "ISR": 30.24714
          }
        },
        {
          "time": 121.0,
          "duration": 1.0,
          "metrics": {
            "SDR": -0.16082,
            "SIR": -0.18494,
            "SAR": 31.31044,
            "ISR": 29.27432
          }
        },
        {
          "time": 122.0,
          "duration": 1.0,
          "metrics": {
            "SDR": -0.29402,
            "SIR": -0.33571,
            "SAR": 31.59385,
            "ISR": 28.79308
          }
        },
        {
          "time": 123.0,
          "duration": 1.0,
          "metrics": {
            "SDR": 0.08421,
            "SIR": 0.07078,
            "SAR": 30.66021,
            "ISR": 31.86787
          }
        },
        {
          "time": 124.0,
          "duration": 1.0,
          "metrics": {
            "SDR": -2.07369,
            "SIR": -2.05018,
            "SAR": 31.33859,
            "ISR": 28.62111
          }
        },
        {
          "time": 125.0,
          "duration": 1.0,
          "metrics": {
            "SDR": -1.02395,
            "SIR": -1.08030,
            "SAR": 32.06757,
            "ISR": 28.48465
          }
        },
        {
          "time": 126.0,
          "duration": 1.0,
          "metrics": {
            "SDR": -1.58429,
            "SIR": -1.61063,
            "SAR": 31.98060,
            "ISR": 27.47829
          }
        },
        {
          "time": 127.0,
          "duration": 1.0,
          "metrics": {
            "SDR": -0.33420,
            "SIR": -0.39761,
            "SAR": 30.41703,
            "ISR": 27.59085
          }
        },
        {
          "time": 128.0,
          "duration": 1.0,
          "metrics": {
            "SDR": -1.01781,
            "SIR": -1.09842,
            "SAR": 30.91977,
            "ISR": 28.41608
          }
        },
        {
          "time": 129.0,
          "duration": 1.0,
          "metrics": {
            "SDR": -2.45583,
            "SIR": -2.50733,
            "SAR": 32.01331,
            "ISR": 28.84089
          }
        },
        {
          "time": 130.0,
          "duration": 1.0,
          "metrics": {
            "SDR": -2.58605,
            "SIR": -2.60687,
            "SAR": 32.28263,
            "ISR": 30.76647
          }
        },
        {
          "time": 131.0,
          "duration": 1.0,
          "metrics": {
            "SDR": -2.53207,
            "SIR": -2.60613,
            "SAR": 32.05359,
            "ISR": 27.76153
          }
        },
        {
          "time": 132.0,
          "duration": 1.0,
          "metrics": {
            "SDR": -0.44931,
            "SIR": -0.50401,
            "SAR": 30.01363,
            "ISR": 26.07831
          }
        },
        {
          "time": 133.0,
          "duration": 1.0,
          "metrics": {
            "SDR": -3.20689,
            "SIR": -2.58236,
            "SAR": 9.16322,
            "ISR": 21.02586
          }
        },
        {
          "time": 134.0,
          "duration": 1.0,
          "metrics": {
            "SDR": -6.27239,
            "SIR": -5.57644,
            "SAR": 9.26483,
            "ISR": 22.98830
          }
        },
        {
          "time": 135.0,
          "duration": 1.0,
          "metrics": {
            "SDR": -7.49163,
            "SIR": -7.03802,
            "SAR": 10.79355,
            "ISR": 21.87990
          }
        },
        {
          "time": 136.0,
          "duration": 1.0,
          "metrics": {
            "SDR": -5.75495,
            "SIR": -5.77310,
            "SAR": 17.27169,
            "ISR": 22.40781
          }
        },
        {
          "time": 137.0,
          "duration": 1.0,
          "metrics": {
            "SDR": -9.98578,
            "SIR": -9.41665,
            "SAR": 9.92834,
            "ISR": 19.05570
          }
        },
        {
          "time": 138.0,
          "duration": 1.0,
          "metrics": {
            "SDR": -7.63468,
            "SIR": -6.70102,
            "SAR": 6.21641,
            "ISR": 19.47038
          }
        },
        {
          "time": 139.0,
          "duration": 1.0,
          "metrics": {
            "SDR": -7.90995,
            "SIR": -7.91399,
            "SAR": 19.36421,
            "ISR": 18.62638
          }
        },
        {
          "time": 140.0,
          "duration": 1.0,
          "metrics": {
            "SDR": -7.17917,
            "SIR": -7.22873,
            "SAR": 33.30956,
            "ISR": 22.21227
          }
        },
        {
          "time": 141.0,
          "duration": 1.0,
          "metrics": {
            "SDR": -5.78010,
            "SIR": -5.38281,
            "SAR": 10.81702,
            "ISR": 21.41340
          }
        },
        {
          "time": 142.0,
          "duration": 1.0,
          "metrics": {
            "SDR": -8.81872,
            "SIR": -7.75084,
            "SAR": 5.91919,
            "ISR": 21.18207
          }
        },
        {
          "time": 143.0,
          "duration": 1.0,
          "metrics": {
            "SDR": -6.31885,
            "SIR": -5.65969,
            "SAR": 8.52454,
            "ISR": 22.53970
          }
        },
        {
          "time": 144.0,
          "duration": 1.0,
          "metrics": {
            "SDR": -9.00517,
            "SIR": -8.33868,
            "SAR": 7.59418,
            "ISR": 21.09131
          }
        },
        {
          "time": 145.0,
          "duration": 1.0,
          "metrics": {
            "SDR": -6.49019,
            "SIR": -6.09162,
            "SAR": 9.68683,
            "ISR": 22.80452
          }
        },
        {
          "time": 146.0,
          "duration": 1.0,
          "metrics": {
            "SDR": -9.91207,
            "SIR": -9.40522,
            "SAR": 9.15635,
            "ISR": 21.08679
          }
        },
        {
          "time": 147.0,
          "duration": 1.0,
          "metrics": {
            "SDR": -7.95297,
            "SIR": -6.91043,
            "SAR": 6.88602,
            "ISR": 20.73156
          }
        },
        {
          "time": 148.0,
          "duration": 1.0,
          "metrics": {
            "SDR": -9.89204,
            "SIR": -9.30232,
            "SAR": 8.55398,
            "ISR": 20.16327
          }
        },
        {
          "time": 149.0,
          "duration": 1.0,
          "metrics": {
            "SDR": -8.15879,
            "SIR": -8.01251,
            "SAR": 12.36135,
            "ISR": 19.82167
          }
        },
        {
          "time": 150.0,
          "duration": 1.0,
          "metrics": {
            "SDR": -8.03092,
            "SIR": -7.97367,
            "SAR": 30.73029,
            "ISR": 21.31366
          }
        },
        {
          "time": 151.0,
          "duration": 1.0,
          "metrics": {
            "SDR": -9.30066,
            "SIR": -8.57810,
            "SAR": 8.06826,
            "ISR": 20.35394
          }
        },
        {
          "time": 152.0,
          "duration": 1.0,
          "metrics": {
            "SDR": -8.31505,
            "SIR": -7.77482,
            "SAR": 9.24680,
            "ISR": 19.62844
          }
        },
        {
          "time": 153.0,
          "duration": 1.0,
          "metrics": {
            "SDR": -9.01664,
            "SIR": -8.53713,
            "SAR": 9.47712,
            "ISR": 19.34719
          }
        },
        {
          "time": 154.0,
          "duration": 1.0,
          "metrics": {
            "SDR": -6.76355,
            "SIR": -6.64868,
            "SAR": 17.21262,
            "ISR": 20.20024
          }
        },
        {
          "time": 155.0,
          "duration": 1.0,
          "metrics": {
            "SDR": -10.75148,
            "SIR": -10.16807,
            "SAR": 8.40343,
            "ISR": 18.62956
          }
        },
        {
          "time": 156.0,
          "duration": 1.0,
          "metrics": {
            "SDR": -6.82660,
            "SIR": -6.03806,
            "SAR": 7.82421,
            "ISR": 20.59141
          }
        },
        {
          "time": 157.0,
          "duration": 1.0,
          "metrics": {
            "SDR": -7.11729,
            "SIR": -7.15394,
            "SAR": 21.60030,
            "ISR": 22.22160
          }
        },
        {
          "time": 158.0,
          "duration": 1.0,
          "metrics": {
            "SDR": -6.80671,
            "SIR": -6.89901,
            "SAR": 33.43669,
            "ISR": 19.85339
          }
        },
        {
          "time": 159.0,
          "duration": 1.0,
          "metrics": {
            "SDR": -8.95247,
            "SIR": -8.36888,
            "SAR": 8.45373,
            "ISR": 20.40193
          }
        },
        {
          "time": 160.0,
          "duration": 1.0,
          "metrics": {
            "SDR": -7.70457,
            "SIR": -6.57987,
            "SAR": 6.27905,
            "ISR": 24.96099
          }
        },
        {
          "time": 161.0,
          "duration": 1.0,
          "metrics": {
            "SDR": -7.32367,
            "SIR": -6.53764,
            "SAR": 7.60503,
            "ISR": 25.40672
          }
        },
        {
          "time": 162.0,
          "duration": 1.0,
          "metrics": {
            "SDR": -8.80804,
            "SIR": -8.32410,
            "SAR": 9.39113,
            "ISR": 21.68198
          }
        },
        {
          "time": 163.0,
          "duration": 1.0,
          "metrics": {
            "SDR": -8.13186,
            "SIR": -7.14996,
            "SAR": 6.60309,
            "ISR": 21.56179
          }
        },
        {
          "time": 164.0,
          "duration": 1.0,
          "metrics": {
            "SDR": -9.93112,
            "SIR": -9.10866,
            "SAR": 7.18250,
            "ISR": 22.07590
          }
        },
        {
          "time": 165.0,
          "duration": 1.0,
          "metrics": {
            "SDR": -9.87758,
            "SIR": -9.38313,
            "SAR": 10.48032,
            "ISR": 21.52001
          }
        },
        {
          "time": 166.0,
          "duration": 1.0,
          "metrics": {
            "SDR": -10.51164,
            "SIR": -10.12204,
            "SAR": 11.09143,
            "ISR": 17.90789
          }
        },
        {
          "time": 167.0,
          "duration": 1.0,
          "metrics": {
            "SDR": -8.94956,
            "SIR": -7.55957,
            "SAR": 5.57335,
            "ISR": 20.70623
          }
        },
        {
          "time": 168.0,
          "duration": 1.0,
          "metrics": {
            "SDR": 13.67797,
            "SIR": 16.65995,
            "SAR": 16.13031,
            "ISR": 26.40273
          }
        },
        {
          "time": 169.0,
          "duration": 1.0,
          "metrics": {
            "SDR": 11.16257,
            "SIR": 11.67781,
            "SAR": 19.95978,
            "ISR": 26.41698
          }
        },
        {
          "time": 170.0,
          "duration": 1.0,
          "metrics": {
            "SDR": 12.42432,
            "SIR": 16.47239,
            "SAR": 13.95938,
            "ISR": 23.74962
          }
        }
      ]
    },
    {
      "name": "accompaniment",
      "frames": [
        {
          "time": 0.0,
          "duration": 1.0,
          "metrics": {
            "SDR": 3.42942,
            "SIR": 49.06107,
            "SAR": 3.42000,
            "ISR": 43.77912
          }
        },
        {
          "time": 1.0,
          "duration": 1.0,
          "metrics": {
            "SDR": 11.27344,
            "SIR": 50.19706,
            "SAR": 11.27233,
            "ISR": 47.53005
          }
        },
        {
          "time": 2.0,
          "duration": 1.0,
          "metrics": {
            "SDR": 25.20983,
            "SIR": 49.07041,
            "SAR": 25.19496,
            "ISR": 47.16618
          }
        },
        {
          "time": 3.0,
          "duration": 1.0,
          "metrics": {
            "SDR": 37.56924,
            "SIR": 49.61012,
            "SAR": 37.40813,
            "ISR": 47.18812
          }
        },
        {
          "time": 4.0,
          "duration": 1.0,
          "metrics": {
            "SDR": 36.73885,
            "SIR": 50.70473,
            "SAR": 36.59463,
            "ISR": 47.24253
          }
        },
        {
          "time": 5.0,
          "duration": 1.0,
          "metrics": {
            "SDR": 9.96043,
            "SIR": 49.68209,
            "SAR": 9.95961,
            "ISR": 47.24962
          }
        },
        {
          "time": 6.0,
          "duration": 1.0,
          "metrics": {
            "SDR": 4.59581,
            "SIR": 46.93257,
            "SAR": 4.60725,
            "ISR": 44.71406
          }
        },
        {
          "time": 7.0,
          "duration": 1.0,
          "metrics": {
            "SDR": 10.81233,
            "SIR": 40.46784,
            "SAR": 10.80447,
            "ISR": 41.73941
          }
        },
        {
          "time": 8.0,
          "duration": 1.0,
          "metrics": {
            "SDR": 33.13146,
            "SIR": 46.00323,
            "SAR": 33.03766,
            "ISR": 44.39646
          }
        },
        {
          "time": 9.0,
          "duration": 1.0,
          "metrics": {
            "SDR": 32.22034,
            "SIR": 45.79173,
            "SAR": 32.01066,
            "ISR": 45.03957
          }
        },
        {
          "time": 10.0,
          "duration": 1.0,
          "metrics": {
            "SDR": 8.89104,
            "SIR": 44.32468,
            "SAR": 8.89936,
            "ISR": 45.71235
          }
        },
        {
          "time": 11.0,
          "duration": 1.0,
          "metrics": {
            "SDR": 6.21995,
            "SIR": 43.28223,
            "SAR": 6.22052,
            "ISR": 42.94781
          }
        },
        {
          "time": 12.0,
          "duration": 1.0,
          "metrics": {
            "SDR": 24.15591,
            "SIR": 45.78824,
            "SAR": 24.11965,
            "ISR": 44.23442
          }
        },
        {
          "time": 13.0,
          "duration": 1.0,
          "metrics": {
            "SDR": 6.33786,
            "SIR": 50.46317,
            "SAR": 6.33135,
            "ISR": 46.72283
          }
        },
        {
          "time": 14.0,
          "duration": 1.0,
          "metrics": {
            "SDR": 14.13020,
            "SIR": 46.01317,
            "SAR": 14.12554,
            "ISR": 45.83299
          }
        },
        {
          "time": 15.0,
          "duration": 1.0,
          "metrics": {
            "SDR": 8.13087,
            "SIR": 51.00046,
            "SAR": 8.13432,
            "ISR": 46.60873
          }
        },
        {
          "time": 16.0,
          "duration": 1.0,
          "metrics": {
            "SDR": 6.75209,
            "SIR": 48.96331,
            "SAR": 6.75263,
            "ISR": 46.59887
          }
        },
        {
          "time": 17.0,
          "duration": 1.0,
          "metrics": {
            "SDR": 10.71440,
            "SIR": 49.27535,
            "SAR": 10.71033,
            "ISR": 47.22011
          }
        },
        {
          "time": 18.0,
          "duration": 1.0,
          "metrics": {
            "SDR": 5.40031,
            "SIR": 41.75108,
            "SAR": 5.39594,
            "ISR": 43.71421
          }
        },
        {
          "time": 19.0,
          "duration": 1.0,
          "metrics": {
            "SDR": 3.45525,
            "SIR": 47.04562,
            "SAR": 3.44736,
            "ISR": 43.89754
          }
        },
        {
          "time": 20.0,
          "duration": 1.0,
          "metrics": {
            "SDR": 9.71514,
            "SIR": 49.50953,
            "SAR": 9.71343,
            "ISR": 47.62693
          }
        },
        {
          "time": 21.0,
          "duration": 1.0,
          "metrics": {
            "SDR": 23.98700,
            "SIR": 51.63183,
            "SAR": 23.97510,
            "ISR": 48.02018
          }
        },
        {
          "time": 22.0,
          "duration": 1.0,
          "metrics": {
            "SDR": 36.34230,
            "SIR": 54.58075,
            "SAR": 36.36830,
            "ISR": 47.75401
          }
        },
        {
          "time": 23.0,
          "duration": 1.0,
          "metrics": {
            "SDR": 36.67476,
            "SIR": 50.80522,
            "SAR": 36.53190,
            "ISR": 47.18399
          }
        },
        {
          "time": 24.0,
          "duration": 1.0,
          "metrics": {
            "SDR": 11.21834,
            "SIR": 49.86698,
            "SAR": 11.21250,
            "ISR": 47.51338
          }
        },
        {
          "time": 25.0,
          "duration": 1.0,
          "metrics": {
            "SDR": 5.77179,
            "SIR": 50.72630,
            "SAR": 5.76763,
            "ISR": 46.72005
          }
        },
        {
          "time": 26.0,
          "duration": 1.0,
          "metrics": {
            "SDR": 9.23428,
            "SIR": 44.35504,
            "SAR": 9.22884,
            "ISR": 44.40965
          }
        },
        {
          "time": 27.0,
          "duration": 1.0,
          "metrics": {
            "SDR": 32.68199,
            "SIR": 47.74626,
            "SAR": 32.60015,
            "ISR": 46.45282
          }
        },
        {
          "time": 28.0,
          "duration": 1.0,
          "metrics": {
            "SDR": 32.93287,
            "SIR": 44.75195,
            "SAR": 32.76419,
            "ISR": 44.40829
          }
        },
        {
          "time": 29.0,
          "duration": 1.0,
          "metrics": {
            "SDR": 9.27920,
            "SIR": 44.38645,
            "SAR": 9.27299,
            "ISR": 45.37540
          }
        },
        {
          "time": 30.0,
          "duration": 1.0,
          "metrics": {
            "SDR": 4.47371,
            "SIR": 47.65290,
            "SAR": 4.47171,
            "ISR": 44.44125
          }
        },
        {
          "time": 31.0,
          "duration": 1.0,
          "metrics": {
            "SDR": 21.90081,
            "SIR": 47.62834,
            "SAR": 21.88868,
            "ISR": 46.15167
          }
        },
        {
          "time": 32.0,
          "duration": 1.0,
          "metrics": {
            "SDR": 8.06733,
            "SIR": 50.48944,
            "SAR": 8.06252,
            "ISR": 46.40341
          }
        },
        {
          "time": 33.0,
          "duration": 1.0,
          "metrics": {
            "SDR": 21.82270,
            "SIR": 48.81152,
            "SAR": 21.80498,
            "ISR": 45.81704
          }
        },
        {
          "time": 34.0,
          "duration": 1.0,
          "metrics": {
            "SDR": 8.66424,
            "SIR": 51.36246,
            "SAR": 8.65831,
            "ISR": 47.32535
          }
        },
        {
          "time": 35.0,
          "duration": 1.0,
          "metrics": {
            "SDR": 8.06821,
            "SIR": 49.42306,
            "SAR": 8.06380,
            "ISR": 46.31171
          }
        },
        {
          "time": 36.0,
          "duration": 1.0,
          "metrics": {
            "SDR": 9.96267,
            "SIR": 50.70670,
            "SAR": 9.95935,
            "ISR": 47.53425
          }
        },
        {
          "time": 37.0,
          "duration": 1.0,
          "metrics": {
            "SDR": 6.25082,
            "SIR": 50.82873,
            "SAR": 6.24667,
            "ISR": 45.18555
          }
        },
        {
          "time": 38.0,
          "duration": 1.0,
          "metrics": {
            "SDR": -0.18772,
            "SIR": 43.24553,
            "SAR": -0.19608,
            "ISR": 43.78252
          }
        },
        {
          "time": 39.0,
          "duration": 1.0,
          "metrics": {
            "SDR": 12.17138,
            "SIR": 48.96427,
            "SAR": 12.16670,
            "ISR": 47.57177
          }
        },
        {
          "time": 40.0,
          "duration": 1.0,
          "metrics": {
            "SDR": 22.14471,
            "SIR": 51.99045,
            "SAR": 22.14199,
            "ISR": 47.65153
          }
        },
        {
          "time": 41.0,
          "duration": 1.0,
          "metrics": {
            "SDR": 21.95764,
            "SIR": 54.59490,
            "SAR": 21.95189,
            "ISR": 48.07686
          }
        },
        {
          "time": 42.0,
          "duration": 1.0,
          "metrics": {
            "SDR": 28.15868,
            "SIR": 52.44368,
            "SAR": 28.13127,
            "ISR": 47.49667
          }
        },
        {
          "time": 43.0,
          "duration": 1.0,
          "metrics": {
            "SDR": 8.46762,
            "SIR": 47.97568,
            "SAR": 8.46517,
            "ISR": 46.79119
          }
        },
        {
          "time": 44.0,
          "duration": 1.0,
          "metrics": {
            "SDR": 5.87048,
            "SIR": 46.95805,
            "SAR": 5.86842,
            "ISR": 45.71680
          }
        },
        {
          "time": 45.0,
          "duration": 1.0,
          "metrics": {
            "SDR": 8.25801,
            "SIR": 46.78098,
            "SAR": 8.25480,
            "ISR": 46.36568
          }
        },
        {
          "time": 46.0,
          "duration": 1.0,
          "metrics": {
            "SDR": 11.51116,
            "SIR": 49.21245,
            "SAR": 11.50700,
            "ISR": 47.11440
          }
        },
        {
          "time": 47.0,
          "duration": 1.0,
          "metrics": {
            "SDR": 19.62664,
            "SIR": 47.33388,
            "SAR": 19.60988,
            "ISR": 46.38301
          }
        },
        {
          "time": 48.0,
          "duration": 1.0,
          "metrics": {
            "SDR": 16.10590,
            "SIR": 49.78730,
            "SAR": 16.09217,
            "ISR": 47.02499
          }
        },
        {
          "time": 49.0,
          "duration": 1.0,
          "metrics": {
            "SDR": 4.09658,
            "SIR": 48.14379,
            "SAR": 4.09208,
            "ISR": 45.01675
          }
        },
        {
          "time": 50.0,
          "duration": 1.0,
          "metrics": {
            "SDR": 17.49768,
            "SIR": 44.63691,
            "SAR": 17.48260,
            "ISR": 45.19792
          }
        },
        {
          "time": 51.0,
          "duration": 1.0,
          "metrics": {
            "SDR": 9.85917,
            "SIR": 49.50975,
            "SAR": 9.85393,
            "ISR": 46.18453
          }
        },
        {
          "time": 52.0,
          "duration": 1.0,
          "metrics": {
            "SDR": 12.34755,
            "SIR": 48.81770,
            "SAR": 12.33822,
            "ISR": 46.04230
          }
        },
        {
          "time": 53.0,
          "duration": 1.0,
          "metrics": {
            "SDR": 11.82801,
            "SIR": 50.57026,
            "SAR": 11.82657,
            "ISR": 46.82231
          }
        },
        {
          "time": 54.0,
          "duration": 1.0,
          "metrics": {
            "SDR": 8.89114,
            "SIR": 49.72210,
            "SAR": 8.88906,
            "ISR": 46.53996
          }
        },
        {
          "time": 55.0,
          "duration": 1.0,
          "metrics": {
            "SDR": 9.02314,
            "SIR": 46.18242,
            "SAR": 9.02033,
            "ISR": 46.31939
          }
        },
        {
          "time": 56.0,
          "duration": 1.0,
          "metrics": {
            "SDR": 12.40047,
            "SIR": 43.93607,
            "SAR": 12.39547,
            "ISR": 45.47448
          }
        },
        {
          "time": 57.0,
          "duration": 1.0,
          "metrics": {
            "SDR": 10.65830,
            "SIR": 42.51180,
            "SAR": 10.66380,
            "ISR": 38.75014
          }
        },
        {
          "time": 58.0,
          "duration": 1.0,
          "metrics": {
            "SDR": 6.67483,
            "SIR": 49.01822,
            "SAR": 6.66398,
            "ISR": 44.62895
          }
        },
        {
          "time": 59.0,
          "duration": 1.0,
          "metrics": {
            "SDR": 6.23519,
            "SIR": 48.08838,
            "SAR": 6.22613,
            "ISR": 44.35431
          }
        },
        {
          "time": 60.0,
          "duration": 1.0,
          "metrics": {
            "SDR": 17.39142,
            "SIR": 51.63657,
            "SAR": 17.38324,
            "ISR": 45.23438
          }
        },
        {
          "time": 61.0,
          "duration": 1.0,
          "metrics": {
            "SDR": 5.46891,
            "SIR": 51.56887,
            "SAR": 5.46351,
            "ISR": 44.71574
          }
        },
        {
          "time": 62.0,
          "duration": 1.0,
          "metrics": {
            "SDR": 11.48918,
            "SIR": 48.78752,
            "SAR": 11.47796,
            "ISR": 44.16808
          }
        },
        {
          "time": 63.0,
          "duration": 1.0,
          "metrics": {
            "SDR": 8.63719,
            "SIR": 53.45594,
            "SAR": 8.63238,
            "ISR": 45.51096
          }
        },
        {
          "time": 64.0,
          "duration": 1.0,
          "metrics": {
            "SDR": 7.99005,
            "SIR": 49.45147,
            "SAR": 7.98600,
            "ISR": 44.56581
          }
        },
        {
          "time": 65.0,
          "duration": 1.0,
          "metrics": {
            "SDR": 12.37455,
            "SIR": 51.13664,
            "SAR": 12.37399,
            "ISR": 43.79796
          }
        },
        {
          "time": 66.0,
          "duration": 1.0,
          "metrics": {
            "SDR": 6.48927,
            "SIR": 51.89898,
            "SAR": 6.48746,
            "ISR": 44.97744
          }
        },
        {
          "time": 67.0,
          "duration": 1.0,
          "metrics": {
            "SDR": 11.91640,
            "SIR": 51.10226,
            "SAR": 11.91363,
            "ISR": 46.04409
          }
        },
        {
          "time": 68.0,
          "duration": 1.0,
          "metrics": {
            "SDR": 8.34604,
            "SIR": 50.75584,
            "SAR": 8.34308,
            "ISR": 45.27416
          }
        },
        {
          "time": 69.0,
          "duration": 1.0,
          "metrics": {
            "SDR": 8.94826,
            "SIR": 49.21563,
            "SAR": 8.94838,
            "ISR": 44.69326
          }
        },
        {
          "time": 70.0,
          "duration": 1.0,
          "metrics": {
            "SDR": 10.49443,
            "SIR": 52.01440,
            "SAR": 10.49079,
            "ISR": 45.22676
          }
        },
        {
          "time": 71.0,
          "duration": 1.0,
          "metrics": {
            "SDR": 7.49343,
            "SIR": 50.81737,
            "SAR": 7.48716,
            "ISR": 45.47057
          }
        },
        {
          "time": 72.0,
          "duration": 1.0,
          "metrics": {
            "SDR": 9.06461,
            "SIR": 47.59925,
            "SAR": 9.06259,
            "ISR": 44.24977
          }
        },
        {
          "time": 73.0,
          "duration": 1.0,
          "metrics": {
            "SDR": 5.84247,
            "SIR": 48.61734,
            "SAR": 5.83419,
            "ISR": 44.45292
          }
        },
        {
          "time": 74.0,
          "duration": 1.0,
          "metrics": {
            "SDR": 8.08246,
            "SIR": 49.97384,
            "SAR": 8.08035,
            "ISR": 44.88983
          }
        },
        {
          "time": 75.0,
          "duration": 1.0,
          "metrics": {
            "SDR": 11.61864,
            "SIR": 49.55832,
            "SAR": 11.61953,
            "ISR": 44.01969
          }
        },
        {
          "time": 76.0,
          "duration": 1.0,
          "metrics": {
            "SDR": 13.11871,
            "SIR": 49.01424,
            "SAR": 13.11129,
            "ISR": 44.96047
          }
        },
        {
          "time": 77.0,
          "duration": 1.0,
          "metrics": {
            "SDR": 9.40276,
            "SIR": 48.01604,
            "SAR": 9.39768,
            "ISR": 44.08862
          }
        },
        {
          "time": 78.0,
          "duration": 1.0,
          "metrics": {
            "SDR": 6.08913,
            "SIR": 48.59878,
            "SAR": 6.08136,
            "ISR": 44.07336
          }
        },
        {
          "time": 79.0,
          "duration": 1.0,
          "metrics": {
            "SDR": 9.36193,
            "SIR": 50.50465,
            "SAR": 9.35910,
            "ISR": 43.49951
          }
        },
        {
          "time": 80.0,
          "duration": 1.0,
          "metrics": {
            "SDR": 6.68892,
            "SIR": 51.46282,
            "SAR": 6.68749,
            "ISR": 44.70231
          }
        },
        {
          "time": 81.0,
          "duration": 1.0,
          "metrics": {
            "SDR": 9.06809,
            "SIR": 46.77833,
            "SAR": 9.06048,
            "ISR": 42.55464
          }
        },
        {
          "time": 82.0,
          "duration": 1.0,
          "metrics": {
            "SDR": 9.54301,
            "SIR": 50.96589,
            "SAR": 9.53898,
            "ISR": 45.48043
          }
        },
        {
          "time": 83.0,
          "duration": 1.0,
          "metrics": {
            "SDR": 8.42735,
            "SIR": 50.67334,
            "SAR": 8.42103,
            "ISR": 44.94775
          }
        },
        {
          "time": 84.0,
          "duration": 1.0,
          "metrics": {
            "SDR": 10.18032,
            "SIR": 52.08121,
            "SAR": 10.17902,
            "ISR": 44.83871
          }
        },
        {
          "time": 85.0,
          "duration": 1.0,
          "metrics": {
            "SDR": 6.29217,
            "SIR": 48.05637,
            "SAR": 6.29158,
            "ISR": 44.78038
          }
        },
        {
          "time": 86.0,
          "duration": 1.0,
          "metrics": {
            "SDR": 9.16369,
            "SIR": 48.77204,
            "SAR": 9.16067,
            "ISR": 44.87721
          }
        },
        {
          "time": 87.0,
          "duration": 1.0,
          "metrics": {
            "SDR": 6.99708,
            "SIR": 52.14261,
            "SAR": 6.99561,
            "ISR": 45.40875
          }
        },
        {
          "time": 88.0,
          "duration": 1.0,
          "metrics": {
            "SDR": 9.21747,
            "SIR": 50.15821,
            "SAR": 9.21059,
            "ISR": 45.51553
          }
        },
        {
          "time": 89.0,
          "duration": 1.0,
          "metrics": {
            "SDR": 7.74375,
            "SIR": 51.34963,
            "SAR": 7.74167,
            "ISR": 45.14902
          }
        },
        {
          "time": 90.0,
          "duration": 1.0,
          "metrics": {
            "SDR": 8.32367,
            "SIR": 46.91367,
            "SAR": 8.31959,
            "ISR": 44.47474
          }
        },
        {
          "time": 91.0,
          "duration": 1.0,
          "metrics": {
            "SDR": 9.82933,
            "SIR": 47.99110,
            "SAR": 9.82294,
            "ISR": 44.83623
          }
        },
        {
          "time": 92.0,
          "duration": 1.0,
          "metrics": {
            "SDR": 7.27410,
            "SIR": 51.47157,
            "SAR": 7.26938,
            "ISR": 45.17367
          }
        },
        {
          "time": 93.0,
          "duration": 1.0,
          "metrics": {
            "SDR": 5.76167,
            "SIR": 50.90318,
            "SAR": 5.75880,
            "ISR": 43.98067
          }
        },
        {
          "time": 94.0,
          "duration": 1.0,
          "metrics": {
            "SDR": 7.56493,
            "SIR": 54.35902,
            "SAR": 7.56273,
            "ISR": 45.41628
          }
        },
        {
          "time": 95.0,
          "duration": 1.0,
          "metrics": {
            "SDR": 9.98258,
            "SIR": 47.56532,
            "SAR": 9.97222,
            "ISR": 44.10134
          }
        },
        {
          "time": 96.0,
          "duration": 1.0,
          "metrics": {
            "SDR": 13.81611,
            "SIR": 48.28190,
            "SAR": 13.80913,
            "ISR": 44.09209
          }
        },
        {
          "time": 97.0,
          "duration": 1.0,
          "metrics": {
            "SDR": 21.73384,
            "SIR": 51.33319,
            "SAR": 21.71744,
            "ISR": 44.43034
          }
        },
        {
          "time": 98.0,
          "duration": 1.0,
          "metrics": {
            "SDR": 27.27361,
            "SIR": 50.02368,
            "SAR": 27.21515,
            "ISR": 44.41419
          }
        },
        {
          "time": 99.0,
          "duration": 1.0,
          "metrics": {
            "SDR": 30.89540,
            "SIR": 48.32895,
            "SAR": 30.74701,
            "ISR": 44.20299
          }
        },
        {
          "time": 100.0,
          "duration": 1.0,
          "metrics": {
            "SDR": 30.67825,
            "SIR": 51.06000,
            "SAR": 30.57476,
            "ISR": 44.93688
          }
        },
        {
          "time": 101.0,
          "duration": 1.0,
          "metrics": {
            "SDR": 30.51545,
            "SIR": 51.25442,
            "SAR": 30.39669,
            "ISR": 44.89189
          }
        },
        {
          "time": 102.0,
          "duration": 1.0,
          "metrics": {
            "SDR": 30.78614,
            "SIR": 47.82472,
            "SAR": 30.56955,
            "ISR": 44.25326
          }
        },
        {
          "time": 103.0,
          "duration": 1.0,
          "metrics": {
            "SDR": 31.55733,
            "SIR": 50.30697,
            "SAR": 31.39814,
            "ISR": 44.48701
          }
        },
        {
          "time": 104.0,
          "duration": 1.0,
          "metrics": {
            "SDR": 30.64678,
            "SIR": 46.31388,
            "SAR": 30.43493,
            "ISR": 43.88180
          }
        },
        {
          "time": 105.0,
          "duration": 1.0,
          "metrics": {
            "SDR": 29.82867,
            "SIR": 47.68224,
            "SAR": 29.68935,
            "ISR": 44.00424
          }
        },
        {
          "time": 106.0,
          "duration": 1.0,
          "metrics": {
            "SDR": 30.63840,
            "SIR": 47.40443,
            "SAR": 30.53676,
            "ISR": 44.62502
          }
        },
        {
          "time": 107.0,
          "duration": 1.0,
          "metrics": {
            "SDR": 31.11931,
            "SIR": 47.09648,
            "SAR": 30.98391,
            "ISR": 44.18076
          }
        },
        {
          "time": 108.0,
          "duration": 1.0,
          "metrics": {
            "SDR": 30.11826,
            "SIR": 51.13236,
            "SAR": 29.99017,
            "ISR": 44.21109
          }
        },
        {
          "time": 109.0,
          "duration": 1.0,
          "metrics": {
            "SDR": 29.93898,
            "SIR": 49.01759,
            "SAR": 29.82755,
            "ISR": 45.25692
          }
        },
        {
          "time": 110.0,
          "duration": 1.0,
          "metrics": {
            "SDR": 31.67258,
            "SIR": 50.35284,
            "SAR": 31.55455,
            "ISR": 45.52411
          }
        },
        {
          "time": 111.0,
          "duration": 1.0,
          "metrics": {
            "SDR": 32.01917,
            "SIR": 49.54598,
            "SAR": 31.87461,
            "ISR": 45.66161
          }
        },
        {
          "time": 112.0,
          "duration": 1.0,
          "metrics": {
            "SDR": 32.02580,
            "SIR": 52.25731,
            "SAR": 31.91932,
            "ISR": 45.61718
          }
        },
        {
          "time": 113.0,
          "duration": 1.0,
          "metrics": {
            "SDR": 31.66849,
            "SIR": 49.84392,
            "SAR": 31.46850,
            "ISR": 45.12812
          }
        },
        {
          "time": 114.0,
          "duration": 1.0,
          "metrics": {
            "SDR": 30.69251,
            "SIR": 48.22666,
            "SAR": 30.56238,
            "ISR": 44.61009
          }
        },
        {
          "time": 115.0,
          "duration": 1.0,
          "metrics": {
            "SDR": 32.01661,
            "SIR": 51.37018,
            "SAR": 31.83871,
            "ISR": 43.99484
          }
        },
        {
          "time": 116.0,
          "duration": 1.0,
          "metrics": {
            "SDR": 32.31879,
            "SIR": 50.48240,
            "SAR": 32.11851,
            "ISR": 44.24834
          }
        },
        {
          "time": 117.0,
          "duration": 1.0,
          "metrics": {
            "SDR": 32.40751,
            "SIR": 50.80246,
            "SAR": 32.24336,
            "ISR": 44.15088
          }
        },
        {
          "time": 118.0,
          "duration": 1.0,
          "metrics": {
            "SDR": 30.98572,
            "SIR": 47.87313,
            "SAR": 30.83467,
            "ISR": 44.48657
          }
        },
        {
          "time": 119.0,
          "duration": 1.0,
          "metrics": {
            "SDR": 30.39905,
            "SIR": 49.63720,
            "SAR": 30.23560,
            "ISR": 44.59613
          }
        },
        {
          "time": 120.0,
          "duration": 1.0,
          "metrics": {
            "SDR": 30.77315,
            "SIR": 50.13976,
            "SAR": 30.63077,
            "ISR": 44.24432
          }
        },
        {
          "time": 121.0,
          "duration": 1.0,
          "metrics": {
            "SDR": 31.42992,
            "SIR": 52.30503,
            "SAR": 31.31044,
            "ISR": 44.52031
          }
        },
        {
          "time": 122.0,
          "duration": 1.0,
          "metrics": {
            "SDR": 31.70589,
            "SIR": 49.83490,
            "SAR": 31.59385,
            "ISR": 44.75308
          }
        },
        {
          "time": 123.0,
          "duration": 1.0,
          "metrics": {
            "SDR": 30.81719,
            "SIR": 49.65408,
            "SAR": 30.66021,
            "ISR": 45.14966
          }
        },
        {
          "time": 124.0,
          "duration": 1.0,
          "metrics": {
            "SDR": 31.46615,
            "SIR": 50.88836,
            "SAR": 31.33859,
            "ISR": 46.17163
          }
        },
        {
          "time": 125.0,
          "duration": 1.0,
          "metrics": {
            "SDR": 32.23953,
            "SIR": 49.12354,
            "SAR": 32.06757,
            "ISR": 46.01116
          }
        },
        {
          "time": 126.0,
          "duration": 1.0,
          "metrics": {
            "SDR": 32.14965,
            "SIR": 50.14015,
            "SAR": 31.98060,
            "ISR": 45.59714
          }
        },
        {
          "time": 127.0,
          "duration": 1.0,
          "metrics": {
            "SDR": 30.55235,
            "SIR": 46.42739,
            "SAR": 30.41703,
            "ISR": 44.55001
          }
        },
        {
          "time": 128.0,
          "duration": 1.0,
          "metrics": {
            "SDR": 31.03228,
            "SIR": 48.72800,
            "SAR": 30.91977,
            "ISR": 45.60527
          }
        },
        {
          "time": 129.0,
          "duration": 1.0,
          "metrics": {
            "SDR": 32.19377,
            "SIR": 48.27154,
            "SAR": 32.01331,
            "ISR": 46.41608
          }
        },
        {
          "time": 130.0,
          "duration": 1.0,
          "metrics": {
            "SDR": 32.42930,
            "SIR": 49.67439,
            "SAR": 32.28263,
            "ISR": 46.34222
          }
        },
        {
          "time": 131.0,
          "duration": 1.0,
          "metrics": {
            "SDR": 32.17820,
            "SIR": 51.67436,
            "SAR": 32.05359,
            "ISR": 46.29521
          }
        },
        {
          "time": 132.0,
          "duration": 1.0,
          "metrics": {
            "SDR": 30.18867,
            "SIR": 45.70819,
            "SAR": 30.01363,
            "ISR": 44.96545
          }
        },
        {
          "time": 133.0,
          "duration": 1.0,
          "metrics": {
            "SDR": 9.16178,
            "SIR": 42.92745,
            "SAR": 9.16322,
            "ISR": 44.74602
          }
        },
        {
          "time": 134.0,
          "duration": 1.0,
          "metrics": {
            "SDR": 9.26785,
            "SIR": 48.01462,
            "SAR": 9.26483,
            "ISR": 44.99877
          }
        },
        {
          "time": 135.0,
          "duration": 1.0,
          "metrics": {
            "SDR": 10.80254,
            "SIR": 40.96588,
            "SAR": 10.79355,
            "ISR": 46.02829
          }
        },
        {
          "time": 136.0,
          "duration": 1.0,
          "metrics": {
            "SDR": 17.26523,
            "SIR": 48.55962,
            "SAR": 17.27169,
            "ISR": 45.85757
          }
        },
        {
          "time": 137.0,
          "duration": 1.0,
          "metrics": {
            "SDR": 9.92091,
            "SIR": 42.40632,
            "SAR": 9.92834,
            "ISR": 46.68899
          }
        },
        {
          "time": 138.0,
          "duration": 1.0,
          "metrics": {
            "SDR": 6.21928,
            "SIR": 45.47754,
            "SAR": 6.21641,
            "ISR": 45.17619
          }
        },
        {
          "time": 139.0,
          "duration": 1.0,
          "metrics": {
            "SDR": 19.36210,
            "SIR": 42.86294,
            "SAR": 19.36421,
            "ISR": 45.63328
          }
        },
        {
          "time": 140.0,
          "duration": 1.0,
          "metrics": {
            "SDR": 33.94722,
            "SIR": 41.94955,
            "SAR": 33.30956,
            "ISR": 45.89563
          }
        },
        {
          "time": 141.0,
          "duration": 1.0,
          "metrics": {
            "SDR": 10.81972,
            "SIR": 43.17281,
            "SAR": 10.81702,
            "ISR": 44.98928
          }
        },
        {
          "time": 142.0,
          "duration": 1.0,
          "metrics": {
            "SDR": 5.92293,
            "SIR": 40.92532,
            "SAR": 5.91919,
            "ISR": 45.25136
          }
        },
        {
          "time": 143.0,
          "duration": 1.0,
          "metrics": {
            "SDR": 8.53393,
            "SIR": 45.30668,
            "SAR": 8.52454,
            "ISR": 44.81969
          }
        },
        {
          "time": 144.0,
          "duration": 1.0,
          "metrics": {
            "SDR": 7.59551,
            "SIR": 39.91661,
            "SAR": 7.59418,
            "ISR": 45.67628
          }
        },
        {
          "time": 145.0,
          "duration": 1.0,
          "metrics": {
            "SDR": 9.69255,
            "SIR": 48.76717,
            "SAR": 9.68683,
            "ISR": 46.31099
          }
        },
        {
          "time": 146.0,
          "duration": 1.0,
          "metrics": {
            "SDR": 9.16327,
            "SIR": 41.68375,
            "SAR": 9.15635,
            "ISR": 46.57055
          }
        },
        {
          "time": 147.0,
          "duration": 1.0,
          "metrics": {
            "SDR": 6.89036,
            "SIR": 45.68596,
            "SAR": 6.88602,
            "ISR": 45.46946
          }
        },
        {
          "time": 148.0,
          "duration": 1.0,
          "metrics": {
            "SDR": 8.55954,
            "SIR": 43.85943,
            "SAR": 8.55398,
            "ISR": 46.33828
          }
        },
        {
          "time": 149.0,
          "duration": 1.0,
          "metrics": {
            "SDR": 12.37036,
            "SIR": 41.21833,
            "SAR": 12.36135,
            "ISR": 45.60425
          }
        },
        {
          "time": 150.0,
          "duration": 1.0,
          "metrics": {
            "SDR": 30.94981,
            "SIR": 43.00030,
            "SAR": 30.73029,
            "ISR": 45.49960
          }
        },
        {
          "time": 151.0,
          "duration": 1.0,
          "metrics": {
            "SDR": 8.07080,
            "SIR": 41.11233,
            "SAR": 8.06826,
            "ISR": 46.04302
          }
        },
        {
          "time": 152.0,
          "duration": 1.0,
          "metrics": {
            "SDR": 9.25344,
            "SIR": 47.13406,
            "SAR": 9.24680,
            "ISR": 45.78043
          }
        },
        {
          "time": 153.0,
          "duration": 1.0,
          "metrics": {
            "SDR": 9.46452,
            "SIR": 40.30467,
            "SAR": 9.47712,
            "ISR": 45.59852
          }
        },
        {
          "time": 154.0,
          "duration": 1.0,
          "metrics": {
            "SDR": 17.22133,
            "SIR": 48.01930,
            "SAR": 17.21262,
            "ISR": 45.93938
          }
        },
        {
          "time": 155.0,
          "duration": 1.0,
          "metrics": {
            "SDR": 8.40501,
            "SIR": 41.55933,
            "SAR": 8.40343,
            "ISR": 46.46208
          }
        },
        {
          "time": 156.0,
          "duration": 1.0,
          "metrics": {
            "SDR": 7.82143,
            "SIR": 45.03456,
            "SAR": 7.82421,
            "ISR": 44.52609
          }
        },
        {
          "time": 157.0,
          "duration": 1.0,
          "metrics": {
            "SDR": 21.65612,
            "SIR": 40.60909,
            "SAR": 21.60030,
            "ISR": 45.33430
          }
        },
        {
          "time": 158.0,
          "duration": 1.0,
          "metrics": {
            "SDR": 34.05951,
            "SIR": 43.61881,
            "SAR": 33.43669,
            "ISR": 45.78325
          }
        },
        {
          "time": 159.0,
          "duration": 1.0,
          "metrics": {
            "SDR": 8.45186,
            "SIR": 44.01403,
            "SAR": 8.45373,
            "ISR": 45.62420
          }
        },
        {
          "time": 160.0,
          "duration": 1.0,
          "metrics": {
            "SDR": 6.28298,
            "SIR": 40.44399,
            "SAR": 6.27905,
            "ISR": 45.32718
          }
        },
        {
          "time": 161.0,
          "duration": 1.0,
          "metrics": {
            "SDR": 7.60635,
            "SIR": 45.37364,
            "SAR": 7.60503,
            "ISR": 45.74021
          }
        },
        {
          "time": 162.0,
          "duration": 1.0,
          "metrics": {
            "SDR": 9.39590,
            "SIR": 40.19613,
            "SAR": 9.39113,
            "ISR": 45.62113
          }
        },
        {
          "time": 163.0,
          "duration": 1.0,
          "metrics": {
            "SDR": 6.60776,
            "SIR": 44.34127,
            "SAR": 6.60309,
            "ISR": 45.10068
          }
        },
        {
          "time": 164.0,
          "duration": 1.0,
          "metrics": {
            "SDR": 7.18753,
            "SIR": 40.65847,
            "SAR": 7.18250,
            "ISR": 45.91641
          }
        },
        {
          "time": 165.0,
          "duration": 1.0,
          "metrics": {
            "SDR": 10.48033,
            "SIR": 47.36157,
            "SAR": 10.48032,
            "ISR": 46.90077
          }
        },
        {
          "time": 166.0,
          "duration": 1.0,
          "metrics": {
            "SDR": 11.08484,
            "SIR": 40.33197,
            "SAR": 11.09143,
            "ISR": 46.40235
          }
        },
        {
          "time": 167.0,
          "duration": 1.0,
          "metrics": {
            "SDR": 5.58003,
            "SIR": 39.42753,
            "SAR": 5.57335,
            "ISR": 44.95906
          }
        },
        {
          "time": 168.0,
          "duration": 1.0,
          "metrics": {
            "SDR": 16.11727,
            "SIR": 46.04077,
            "SAR": 16.13031,
            "ISR": 42.99144
          }
        },
        {
          "time": 169.0,
          "duration": 1.0,
          "metrics": {
            "SDR": 19.97977,
            "SIR": 48.57984,
            "SAR": 19.95978,
            "ISR": 43.50409
          }
        },
        {
          "time": 170.0,
          "duration": 1.0,
          "metrics": {
            "SDR": 13.98419,
            "SIR": 44.38863,
            "SAR": 13.95938,
            "ISR": 41.60596
          }
        }
      ]
    }
  ],
  "museval_version": "0.4.0"
}